Metadata-Version: 2.1
Name: pandacord
Version: 2.0.0
Summary: A Discord multi-tool.
Home-page: 
Author: ozzy0xd
Author-email: grayozzy11@gmail.com
License: MIT
Keywords: discord
Classifier: Development Status :: 5 - Production/Stable
Classifier: Intended Audience :: Education
Classifier: Operating System :: Microsoft :: Windows :: Windows 10
Classifier: License :: OSI Approved :: MIT License
Classifier: Programming Language :: Python :: 3
License-File: LICENSE.txt
Requires-Dist: requests
Requires-Dist: tls_client
Requires-Dist: typing
